.bifu.yml
bifu/__init__.py
bifu/classes/application.py
bifu/classes/config.py
bifu/classes/errors.py
bifu/classes/pre.py
bifu/classes/printer.py
bifu/classes/process.py
bifu/main.py
bifu-22.4.21.dist-info/entry_points.txt
bifu-22.4.21.dist-info/WHEEL
bifu-22.4.21.dist-info/METADATA
bifu-22.4.21.dist-info/RECORD
