Metadata-Version: 2.1
Name: bifu
Version: 22.4.21
Summary: B.I.F.U. - simple command runner and repository guardian
Home-page: http://github.com/8tm/bifu
Author: Tadeusz Miszczyk
Author-email: 42252259+8tm@users.noreply.github.com
Requires-Python: >=3.7,<4.0
Classifier: Environment :: Console
Classifier: Intended Audience :: Developers
Classifier: Operating System :: Unix
Classifier: Programming Language :: Python :: 3
Classifier: Programming Language :: Python :: 3 :: Only
Classifier: Programming Language :: Python :: 3.7
Classifier: Programming Language :: Python :: 3.8
Classifier: Programming Language :: Python :: 3.9
Requires-Dist: PyYAML (>=6.0,<7.0)
Requires-Dist: munch (>=2.5.0,<3.0.0)
Requires-Dist: pygit2 (>=1.7.2,<2.0.0)
Requires-Dist: requests (>=2.27.1,<3.0.0)
Requires-Dist: types-PyYAML (>=6.0.3,<7.0.0)
Requires-Dist: types-requests (>=2.27.19,<3.0.0)
Project-URL: Documentation, https://test.pypi.org/project/bifu
Project-URL: Repository, http://github.com/8tm/bifu
